Metadata-Version: 1.1
Name: django2-wysiwyg-redactor
Version: 1.0.0
Summary: django-wysiwyg-redactor is a lightweight responsive wysiwyg editor for Django
Home-page: https://github.com/alonraiz/django2-wysiwyg-redactor
Author: Alon Raizman
Author-email: UNKNOWN
License: MIT
Keywords: django,admin,wysiwyg,editor,redactor,redactorjs
Platform: UNKNOWN
Classifier: Development Status :: 5 - Production/Stable
Classifier: Environment :: Web Environment
Classifier: Framework :: Django
Classifier: Intended Audience :: Developers
Classifier: License :: OSI Approved :: BSD License
Classifier: Operating System :: OS Independent
Classifier: Programming Language :: Python
Classifier: Programming Language :: Python :: 3
